dapodix/__init__.py
dapodix/__main__.py
dapodix/click_context.py
dapodix/gui/__init__.py
dapodix/gui/login.py
dapodix/gui/main.py
dapodix/peserta_didik/__init__.py
dapodix/peserta_didik/eksport.py
dapodix/peserta_didik/excel.py
dapodix/peserta_didik/kembali_bersekolah.py
dapodix/peserta_didik/random_longitudinal.py
dapodix/peserta_didik/registrasi.py
dapodix/utils.py
dapodix/version.py
LICENSE
LISENSI
README.md
dapodix-0.4.0.dist-info/entry_points.txt
dapodix-0.4.0.dist-info/LICENSE
dapodix-0.4.0.dist-info/WHEEL
dapodix-0.4.0.dist-info/METADATA
dapodix-0.4.0.dist-info/RECORD
