Metadata-Version: 2.1
Name: dapodix
Version: 0.4.0
Summary: Alat bantu aplikasi Dapodik kemdikbud
Home-page: https://github.com/hexatester/dapodix
License: MIT
Author: hexatester
Author-email: hexatester@protonmail.com
Requires-Python: >=3.7,<4.0
Classifier: Development Status :: 4 - Beta
Classifier: License :: OSI Approved :: MIT License
Classifier: Programming Language :: Python
Classifier: Programming Language :: Python :: 3
Classifier: Programming Language :: Python :: 3.7
Classifier: Programming Language :: Python :: 3.8
Classifier: Programming Language :: Python :: 3.9
Classifier: Topic :: Education
Requires-Dist: cachetools (>=4.2.2,<5.0.0)
Requires-Dist: click (>=8.0.1,<9.0.0)
Requires-Dist: dapodik (>=0.16.6,<0.17.0)
Requires-Dist: openpyxl (>=3.0.7,<4.0.0)
Project-URL: Repository, https://github.com/hexatester/dapodix
